grapresso/__init__.py
grapresso/backends/__init__.py
grapresso/backends/api.py
grapresso/backends/memory.py
grapresso/backends/networkx.py
grapresso/components/__init__.py
grapresso/components/api.py
grapresso/components/edge.py
grapresso/components/graph.py
grapresso/components/node.py
grapresso/components/path.py
grapresso/datastruct/__init__.py
grapresso/datastruct/disjointset.py
grapresso/tools/__init__.py
grapresso/tools/memory.py
grapresso/tools/performance.py
grapresso-0.1.1.dist-info/LICENSE
grapresso-0.1.1.dist-info/METADATA
grapresso-0.1.1.dist-info/WHEEL
grapresso-0.1.1.dist-info/top_level.txt
grapresso-0.1.1.dist-info/zip-safe
grapresso-0.1.1.dist-info/RECORD
