Metadata-Version: 2.1
Name: grapresso
Version: 0.1.1
Summary: Graph + Espresso = Caffeinated Python graph data structure library!
Home-page: https://github.com/kdevo/grapresso
Author: kdevo
Author-email: 
License: GPL-3.0
Project-URL: Bug Tracker, https://github.com/kdevo/grapresso/issues
Project-URL: Documentation, https://github.com/kdevo/grapresso/blob/master/README.md
Project-URL: Source Code, https://github.com/kdevo/grapresso
Project-URL: Download ZIP, https://api.github.com/repos/kdevo/grapresso/zipball
Keywords: graph-algorithms graph-theory graph-datastructure storage-format pluggable-backends
Platform: UNKNOWN
Requires-Python: >=3.6
Provides-Extra: backend-networkx
Requires-Dist: networkx (==2.4.0) ; extra == 'backend-networkx'
Provides-Extra: test
Requires-Dist: pytest (<6.0.0,>=5.0.0) ; extra == 'test'
